positionrepo/__init__.py
positionrepo/repository/PositionRepository.py
positionrepo/repository/PositionSlipRepository.py
positionrepo/repository/__init__.py
positionrepo/repository/serialize/__init__.py
positionrepo/repository/serialize/position_deserializer.py
positionrepo/repository/serialize/position_serializer.py
positionrepo/repository/serialize/position_slip_deserializer.py
positionrepo/repository/serialize/position_slip_serializer.py
persuader_technology_automata_position_repository-0.1.6.dist-info/LICENSE
persuader_technology_automata_position_repository-0.1.6.dist-info/METADATA
persuader_technology_automata_position_repository-0.1.6.dist-info/WHEEL
persuader_technology_automata_position_repository-0.1.6.dist-info/top_level.txt
persuader_technology_automata_position_repository-0.1.6.dist-info/RECORD
